[
  {
    "id": 1,
    "name": "Puesto Santa Clara",
    "tags": ["Italian", "Latin"],
    "image": "puestosantaclara.jpg"
  },
  {
    "id": 2,
    "name": "Ramen Taka",
    "tags": ["Japanese", "Asian", "ramen"],
    "image": "ramentaka.jpg"
  },
  {
    "id": 3,
    "name": "Din Tai Fung",
    "tags": ["Chinese", "Asian"],
    "image": "dintaifung.jpg"
  },
  {
    "id": 4,
    "name": "Athena Grill",
    "tags": ["Greek", "bowls", "lunch"],
    "image": "athena-grill.jpg"
  },
  {
    "id": 5,
    "name": "Fleming's Prime Steakhouse and Wine Bar",
    "tags": ["Steakhouse", "Bar"],
    "image": "flemings.jpg"
  },
  {
    "id": 6,
    "name": "Mission City Grill",
    "tags": ["American", "Bar"],
    "image": "missioncitygrill.jpg"
  }
]
